{
    "apple-font": {
        "cargoLock": null,
        "date": null,
        "extract": null,
        "name": "apple-font",
        "passthru": null,
        "pinned": false,
        "src": {
            "sha256": "sha256-SeTLhl6iFkCDowM87/BTa3mnknngjKpwY89wx8rOQGU=",
            "type": "tarball",
            "url": "https://s3.onelock.org/download/fonts/apple-nerd.tar.gz"
        },
        "version": "https://s3.onelock.org/download/fonts/apple-nerd.tar.gz"
    },
    "apple-font-emoji": {
        "cargoLock": null,
        "date": null,
        "extract": null,
        "name": "apple-font-emoji",
        "passthru": null,
        "pinned": false,
        "src": {
            "name": null,
            "sha256": "sha256-U1oEOvBHBtJEcQWeZHRb/IDWYXraLuo0NdxWINwPUxg=",
            "type": "url",
            "url": "https://github.com/samuelngs/apple-emoji-linux/releases/latest/download/AppleColorEmoji-Linux.ttf"
        },
        "version": "https://github.com/samuelngs/apple-emoji-linux/releases/latest/download/AppleColorEmoji-Linux.ttf"
    },
    "fsel": {
        "cargoLock": null,
        "date": "2026-04-19",
        "extract": null,
        "name": "fsel",
        "passthru": null,
        "pinned": false,
        "src": {
            "deepClone": false,
            "fetchSubmodules": false,
            "leaveDotGit": false,
            "name": null,
            "owner": "Mjoyufull",
            "repo": "fsel",
            "rev": "ad49c5d96bb1b1b738c5ce6f4410ecffea8adb5c",
            "sha256": "sha256-pBQMSlEUICEfmzA+oSonzH0JlAcBjsVE0gT0QwsTNFE=",
            "sparseCheckout": [],
            "type": "github"
        },
        "version": "ad49c5d96bb1b1b738c5ce6f4410ecffea8adb5c"
    },
    "fuzzy-search": {
        "cargoLock": null,
        "date": "2026-03-25",
        "extract": null,
        "name": "fuzzy-search",
        "passthru": null,
        "pinned": false,
        "src": {
            "deepClone": false,
            "fetchSubmodules": false,
            "leaveDotGit": false,
            "name": null,
            "owner": "onelocked",
            "repo": "fuzzy-search.yazi",
            "rev": "16cea088a39c7769fbd22c4810347b04dd38c6b2",
            "sha256": "sha256-3YsZQ7SOkJZfUWP2KGzp8fPpT42M+x2aThs/AYmdy0o=",
            "sparseCheckout": [],
            "type": "github"
        },
        "version": "16cea088a39c7769fbd22c4810347b04dd38c6b2"
    },
    "grubTheme": {
        "cargoLock": null,
        "date": "2026-01-11",
        "extract": null,
        "name": "grubTheme",
        "passthru": null,
        "pinned": false,
        "src": {
            "deepClone": false,
            "fetchSubmodules": false,
            "leaveDotGit": false,
            "name": null,
            "owner": "onelocked",
            "repo": "grub2-theme",
            "rev": "207dfe09411f08916666acf65bf6262e5ef5e6d0",
            "sha256": "sha256-ChnML4zm4EnVX/WmZW5RWHnK/tqjXSeR4BK8XfN0xxA=",
            "sparseCheckout": [],
            "type": "github"
        },
        "version": "207dfe09411f08916666acf65bf6262e5ef5e6d0"
    },
    "otter-launcher": {
        "cargoLock": null,
        "date": "2026-04-23",
        "extract": null,
        "name": "otter-launcher",
        "passthru": null,
        "pinned": false,
        "src": {
            "deepClone": false,
            "fetchSubmodules": false,
            "leaveDotGit": false,
            "name": null,
            "owner": "kuokuo123",
            "repo": "otter-launcher",
            "rev": "ae647cef5b3c3dd52bedd7a8c881988e412a2dca",
            "sha256": "sha256-ImJeI5xbd/w4nchFwc0tSS8v2vYWx/ttwM5uk2BWsCk=",
            "sparseCheckout": [],
            "type": "github"
        },
        "version": "ae647cef5b3c3dd52bedd7a8c881988e412a2dca"
    },
    "tmuxFloax": {
        "cargoLock": null,
        "date": "2026-02-24",
        "extract": null,
        "name": "tmuxFloax",
        "passthru": null,
        "pinned": false,
        "src": {
            "deepClone": false,
            "fetchSubmodules": false,
            "leaveDotGit": false,
            "name": null,
            "owner": "omerxx",
            "repo": "tmux-floax",
            "rev": "133f526793d90d2caa323c47687dd5544a2c704b",
            "sha256": "sha256-9Hb9dn2qHF6KcIhtogvycX3Z0MoQrLPLCzZXtjGlPHw=",
            "sparseCheckout": [],
            "type": "github"
        },
        "version": "133f526793d90d2caa323c47687dd5544a2c704b"
    },
    "zen-theme-store": {
        "cargoLock": null,
        "date": "2026-03-11",
        "extract": null,
        "name": "zen-theme-store",
        "passthru": null,
        "pinned": false,
        "src": {
            "deepClone": false,
            "fetchSubmodules": false,
            "leaveDotGit": false,
            "name": null,
            "owner": "zen-browser",
            "repo": "theme-store",
            "rev": "7173dba5d060417fd65764b706856ae609496e31",
            "sha256": "sha256-Vq0AboLzase+tTZ1Erf2cKpF55cm3eHNuXmmQuOknvw=",
            "sparseCheckout": [],
            "type": "github"
        },
        "version": "7173dba5d060417fd65764b706856ae609496e31"
    }
}